{
  "date": "2026-04-23",
  "sources": {
    "oil_brent_usd": 103.4,
    "natural_gas_eur_mwh": 58,
    "urea_usd_ton": 480,
    "methanol_usd_ton": 540
  },
  "foods": [
    {
      "id": "chicken",
      "crisis_exposure_pct": 58
    },
    {
      "id": "bread",
      "crisis_exposure_pct": 45
    },
    {
      "id": "tomatoes",
      "crisis_exposure_pct": 43
    },
    {
      "id": "salmon",
      "crisis_exposure_pct": 56
    },
    {
      "id": "rice",
      "crisis_exposure_pct": 16
    },
    {
      "id": "pasta",
      "crisis_exposure_pct": 40
    },
    {
      "id": "flour",
      "crisis_exposure_pct": 38
    },
    {
      "id": "oats",
      "crisis_exposure_pct": 16
    },
    {
      "id": "cornflakes",
      "crisis_exposure_pct": 45
    },
    {
      "id": "couscous",
      "crisis_exposure_pct": 40
    },
    {
      "id": "noodles",
      "crisis_exposure_pct": 45
    },
    {
      "id": "crackers",
      "crisis_exposure_pct": 45
    },
    {
      "id": "beef",
      "crisis_exposure_pct": 58
    },
    {
      "id": "pork",
      "crisis_exposure_pct": 19
    },
    {
      "id": "lamb",
      "crisis_exposure_pct": 19
    },
    {
      "id": "turkey",
      "crisis_exposure_pct": 19
    },
    {
      "id": "sausages",
      "crisis_exposure_pct": 58
    },
    {
      "id": "milk",
      "crisis_exposure_pct": 24
    },
    {
      "id": "cheese",
      "crisis_exposure_pct": 55
    },
    {
      "id": "butter",
      "crisis_exposure_pct": 36
    },
    {
      "id": "yoghurt",
      "crisis_exposure_pct": 55
    },
    {
      "id": "eggs",
      "crisis_exposure_pct": 42
    },
    {
      "id": "cream",
      "crisis_exposure_pct": 55
    },
    {
      "id": "potatoes",
      "crisis_exposure_pct": 34
    },
    {
      "id": "onions",
      "crisis_exposure_pct": 40
    },
    {
      "id": "bananas",
      "crisis_exposure_pct": 34
    },
    {
      "id": "apples",
      "crisis_exposure_pct": 45
    },
    {
      "id": "oranges",
      "crisis_exposure_pct": 36
    },
    {
      "id": "lettuce",
      "crisis_exposure_pct": 26
    },
    {
      "id": "peppers",
      "crisis_exposure_pct": 43
    },
    {
      "id": "carrots",
      "crisis_exposure_pct": 31
    },
    {
      "id": "avocado",
      "crisis_exposure_pct": 47
    },
    {
      "id": "garlic",
      "crisis_exposure_pct": 34
    },
    {
      "id": "cucumber",
      "crisis_exposure_pct": 55
    },
    {
      "id": "shrimp",
      "crisis_exposure_pct": 52
    },
    {
      "id": "canned_sardines",
      "crisis_exposure_pct": 51
    },
    {
      "id": "cod",
      "crisis_exposure_pct": 51
    },
    {
      "id": "canned_tuna",
      "crisis_exposure_pct": 47
    },
    {
      "id": "cooking_oil",
      "crisis_exposure_pct": 50
    },
    {
      "id": "frozen_pizza",
      "crisis_exposure_pct": 55
    },
    {
      "id": "chocolate",
      "crisis_exposure_pct": 50
    },
    {
      "id": "crisps",
      "crisis_exposure_pct": 50
    },
    {
      "id": "biscuits",
      "crisis_exposure_pct": 50
    },
    {
      "id": "soft_drinks",
      "crisis_exposure_pct": 50
    },
    {
      "id": "beer",
      "crisis_exposure_pct": 50
    },
    {
      "id": "coffee",
      "crisis_exposure_pct": 60
    },
    {
      "id": "sugar",
      "crisis_exposure_pct": 45
    },
    {
      "id": "peanut_butter",
      "crisis_exposure_pct": 50
    },
    {
      "id": "orange_juice",
      "crisis_exposure_pct": 1
    },
    {
      "id": "mayonnaise",
      "crisis_exposure_pct": 2
    },
    {
      "id": "tomato_sauce",
      "crisis_exposure_pct": 50
    },
    {
      "id": "baby_formula",
      "crisis_exposure_pct": 50
    },
    {
      "id": "lentils",
      "crisis_exposure_pct": 10
    },
    {
      "id": "chickpeas",
      "crisis_exposure_pct": 10
    },
    {
      "id": "tofu",
      "crisis_exposure_pct": 40
    },
    {
      "id": "beans",
      "crisis_exposure_pct": 8
    },
    {
      "id": "quinoa",
      "crisis_exposure_pct": 5
    },
    {
      "id": "olive_oil",
      "crisis_exposure_pct": 6
    },
    {
      "id": "frozen_peas",
      "crisis_exposure_pct": 34
    }
  ]
}
